pifx/__init__.py
pifx/core.pyc
pifx/core.py
pifx/util.py
pifx/util.pyc
pifx/__init__.pyc
pifx/constants.pyc
pifx/constants.py
pifx/client.py
pifx/client.pyc
pifx-1.0.1.dist-info/METADATA
pifx-1.0.1.dist-info/WHEEL
pifx-1.0.1.dist-info/metadata.json
pifx-1.0.1.dist-info/RECORD
pifx-1.0.1.dist-info/DESCRIPTION.rst
pifx-1.0.1.dist-info/top_level.txt
