Metadata-Version: 2.0
Name: pifx
Version: 1.0.1
Summary: PIFX is a Python library for the LIFX cloud HTTP API
Home-page: https://github.com/cydrobolt/pifx
Author: Chaoyi Zha
Author-email: me@cydrobolt.com
License: Apache v2
Keywords: lifx iot library lights sdk
Platform: UNKNOWN
Classifier: Development Status :: 5 - Production/Stable
Classifier: Intended Audience :: Developers
Classifier: License :: OSI Approved :: Apache Software License
Classifier: Topic :: Software Development :: Libraries
Classifier: Programming Language :: Python :: 2
Classifier: Programming Language :: Python :: 3
Requires-Dist: requests
Requires-Dist: six
